shark_games/__init__.py
shark_games/cli.py
shark_games/main.py
shark_games/dices/__init__.py
shark_games/dices/coin.py
shark_games/dices/roll.py
shark_games/praise/__init__.py
shark_games/praise/praise.py
shark_games-0.2.4.dist-info/LICENSE
shark_games-0.2.4.dist-info/METADATA
shark_games-0.2.4.dist-info/WHEEL
shark_games-0.2.4.dist-info/entry_points.txt
shark_games-0.2.4.dist-info/top_level.txt
shark_games-0.2.4.dist-info/RECORD
