Metadata-Version: 2.1
Name: shark_games
Version: 0.2.4
Summary: Games bot for Sharkey hosted on @games@woem.men
Author-email: sophie <itsme@itssophi.ee>
License: GNU GENERAL PUBLIC LICENSE
Project-URL: Repository, https://codeberg.org/itssophie/shark-games
Project-URL: Issues, https://codeberg.org/itssophie/shark-games/issues
Project-URL: Changelog, https://codeberg.org/itssophie/shark-games/src/branch/main/CHANGELOG.md
Keywords: Sharkey,Fediverse,bot,games
Classifier: Development Status :: 4 - Beta
Classifier: Framework :: AsyncIO
Classifier: Intended Audience :: Developers
Classifier: Natural Language :: English
Classifier: License :: OSI Approved :: GNU General Public License v3 or later (GPLv3+)
Classifier: Programming Language :: Python :: 3
Classifier: Programming Language :: Python :: 3.12
Requires-Python: >=3.12
License-File: LICENSE
Requires-Dist: click
Requires-Dist: aiohttp
Requires-Dist: aiodns
Requires-Dist: Brotli
Requires-Dist: requests
Requires-Dist: aiofiles
Requires-Dist: dice
